rk_utils/__init__.py
rk_utils/skeleton.py
rk_utils-0.0.2.dist-info/LICENSE.txt
rk_utils-0.0.2.dist-info/METADATA
rk_utils-0.0.2.dist-info/WHEEL
rk_utils-0.0.2.dist-info/top_level.txt
rk_utils-0.0.2.dist-info/RECORD
