Metadata-Version: 2.1
Name: rk-utils
Version: 0.0.2
Summary: Some useful Python utilities made by RKWS.
Home-page: https://github.com/opposj/Rk-Utils
Author: opposj
Author-email: 18965385801@163.com
License: MIT
Project-URL: Documentation, https://pyscaffold.org/
Platform: any
Classifier: Development Status :: 4 - Beta
Classifier: Programming Language :: Python
License-File: LICENSE.txt
Requires-Dist: importlib-metadata ; python_version < "3.8"
Provides-Extra: testing
Requires-Dist: setuptools ; extra == 'testing'
Requires-Dist: pytest ; extra == 'testing'
Requires-Dist: pytest-cov ; extra == 'testing'
